{
  "$schema": "./_schema.json",
  "labName": "Basic Purview Lab",
  "prefix": "PVLab",
  "domain": "MngEnvMCAP648165.onmicrosoft.com",
  "workloads": {
    "testUsers": {
      "enabled": true,
      "users": [
        {
          "upn": "rtorres@MngEnvMCAP648165.onmicrosoft.com"
        },
        {
          "upn": "mchen@MngEnvMCAP648165.onmicrosoft.com"
        },
        {
          "upn": "nbrooks@MngEnvMCAP648165.onmicrosoft.com"
        },
        {
          "upn": "dokafor@MngEnvMCAP648165.onmicrosoft.com"
        },
        {
          "upn": "sreeves@MngEnvMCAP648165.onmicrosoft.com"
        },
        {
          "upn": "jblake@MngEnvMCAP648165.onmicrosoft.com"
        },
        {
          "upn": "msullivan@MngEnvMCAP648165.onmicrosoft.com"
        },
        {
          "upn": "pnair@MngEnvMCAP648165.onmicrosoft.com"
        }
      ],
      "groups": [
        {
          "displayName": "PVLab-Executives",
          "members": [
            "jblake",
            "sreeves"
          ]
        },
        {
          "displayName": "PVLab-Finance-Team",
          "members": [
            "mchen",
            "jblake"
          ]
        },
        {
          "displayName": "PVLab-Legal-Team",
          "members": [
            "nbrooks",
            "rtorres",
            "pnair"
          ]
        }
      ],
      "mode": "existing"
    },
    "dlp": {
      "enabled": true,
      "policies": [
        {
          "name": "US PII Protection",
          "locations": [
            "Exchange",
            "SharePoint",
            "OneDrive",
            "Teams"
          ],
          "rules": [
            {
              "name": "Detect Social Security Numbers",
              "sensitiveInfoTypes": [
                "U.S. Social Security Number (SSN)"
              ],
              "minCount": 5,
              "enforcement": {
                "action": "block",
                "userNotification": {
                  "enabled": true,
                  "message": "This content matches a DLP policy. Contact your compliance team if you believe this is in error."
                },
                "alert": {
                  "enabled": true,
                  "severity": "medium"
                }
              }
            },
            {
              "name": "Detect Credit Card Numbers",
              "sensitiveInfoTypes": [
                "Credit Card Number"
              ],
              "minCount": 5,
              "enforcement": {
                "action": "block",
                "userNotification": {
                  "enabled": true,
                  "message": "This content matches a DLP policy. Contact your compliance team if you believe this is in error."
                },
                "alert": {
                  "enabled": true,
                  "severity": "medium"
                }
              }
            }
          ]
        },
        {
          "name": "Financial Data Protection",
          "locations": [
            "Exchange",
            "SharePoint",
            "OneDrive",
            "Teams"
          ],
          "appliesToGroups": [
            "PVLab-Finance-Team"
          ],
          "rules": [
            {
              "name": "Detect Bank Account Numbers",
              "sensitiveInfoTypes": [
                "U.S. Bank Account Number"
              ],
              "minCount": 1,
              "enforcement": {
                "action": "block",
                "userNotification": {
                  "enabled": true,
                  "message": "This content matches a DLP policy. Contact your compliance team if you believe this is in error."
                },
                "alert": {
                  "enabled": true,
                  "severity": "medium"
                }
              }
            },
            {
              "name": "Detect Credit Cards in Financial Comms",
              "sensitiveInfoTypes": [
                "Credit Card Number"
              ],
              "minCount": 1,
              "enforcement": {
                "action": "block",
                "userNotification": {
                  "enabled": true,
                  "message": "This content matches a DLP policy. Contact your compliance team if you believe this is in error."
                },
                "alert": {
                  "enabled": true,
                  "severity": "medium"
                }
              }
            }
          ]
        },
        {
          "name": "HR Case Data Protection",
          "locations": [
            "Exchange",
            "SharePoint",
            "OneDrive",
            "Teams"
          ],
          "appliesToGroups": [
            "PVLab-Legal-Team"
          ],
          "rules": [
            {
              "name": "Detect SSNs in HR Case Files",
              "sensitiveInfoTypes": [
                "U.S. Social Security Number (SSN)"
              ],
              "minCount": 1,
              "enforcement": {
                "action": "block",
                "userNotification": {
                  "enabled": true,
                  "message": "This content matches a DLP policy. Contact your compliance team if you believe this is in error."
                },
                "alert": {
                  "enabled": true,
                  "severity": "medium"
                }
              }
            },
            {
              "name": "Detect Bank Account Data in HR Cases",
              "sensitiveInfoTypes": [
                "U.S. Bank Account Number"
              ],
              "minCount": 1,
              "enforcement": {
                "action": "block",
                "userNotification": {
                  "enabled": true,
                  "message": "This content matches a DLP policy. Contact your compliance team if you believe this is in error."
                },
                "alert": {
                  "enabled": true,
                  "severity": "medium"
                }
              }
            }
          ]
        },
        {
          "name": "Workplace Health Record Protection",
          "locations": [
            "Exchange",
            "SharePoint",
            "OneDrive",
            "Teams"
          ],
          "rules": [
            {
              "name": "Detect Medical Terms in Workplace Health Records",
              "sensitiveInfoTypes": [
                "All Medical Terms And Conditions"
              ],
              "minCount": 1,
              "enforcement": {
                "action": "block",
                "userNotification": {
                  "enabled": true,
                  "message": "This content matches a DLP policy. Contact your compliance team if you believe this is in error."
                },
                "alert": {
                  "enabled": true,
                  "severity": "medium"
                }
              }
            },
            {
              "name": "Detect SSNs in Workplace Health Records",
              "sensitiveInfoTypes": [
                "U.S. Social Security Number (SSN)"
              ],
              "minCount": 1,
              "enforcement": {
                "action": "block",
                "userNotification": {
                  "enabled": true,
                  "message": "This content matches a DLP policy. Contact your compliance team if you believe this is in error."
                },
                "alert": {
                  "enabled": true,
                  "severity": "medium"
                }
              }
            }
          ]
        },
        {
          "name": "Confidential Label Egress Block",
          "locations": [
            "Exchange",
            "SharePoint",
            "OneDrive",
            "Teams"
          ],
          "rules": [
            {
              "name": "Block external sharing of Highly Confidential Regulated-Data",
              "labels": [
                "Highly Confidential\\Regulated-Data"
              ],
              "enforcement": {
                "action": "block",
                "userNotification": {
                  "enabled": true,
                  "message": "Content labeled Highly Confidential / Regulated-Data cannot be shared externally. Contact compliance for an exception."
                },
                "alert": {
                  "enabled": true,
                  "severity": "high"
                }
              }
            }
          ]
        }
      ]
    },
    "sensitivityLabels": {
      "enabled": true,
      "labels": [
        {
          "name": "Confidential",
          "tooltip": "Data that requires protection and is intended for internal use only",
          "color": "#0078D4",
          "sublabels": [
            {
              "name": "Internal",
              "tooltip": "Internal-use only - all employees",
              "encryption": false,
              "contentMarking": {
                "headerText": "CONFIDENTIAL - Internal",
                "footerText": "Do not share outside the organization"
              }
            },
            {
              "name": "Recipients-Only",
              "tooltip": "Encrypted - accessible only to named recipients",
              "encryption": true,
              "contentMarking": {
                "headerText": "CONFIDENTIAL - Recipients Only",
                "footerText": "Encrypted and restricted to named recipients"
              }
            },
            {
              "name": "Anyone-No-Forwarding",
              "tooltip": "Encrypted - recipients can read but cannot forward, copy, or print",
              "encryption": true,
              "contentMarking": {
                "headerText": "CONFIDENTIAL - Do Not Forward",
                "footerText": "Forwarding, copying, and printing are disabled"
              }
            },
            {
              "name": "Regulated-Data",
              "tooltip": "Encrypted - regulated data (PII, PCI, financial). Block external egress.",
              "encryption": true,
              "contentMarking": {
                "headerText": "CONFIDENTIAL - Regulated Data",
                "footerText": "Subject to regulatory protection (PII / PCI / financial). Restricted distribution."
              }
            },
            {
              "name": "Vertical-Specific",
              "tooltip": "Encrypted - vertical-specific scoping (e.g., medical, HR). Restricted to authorized teams.",
              "encryption": true,
              "contentMarking": {
                "headerText": "CONFIDENTIAL - Vertical-Specific",
                "footerText": "Restricted to authorized vertical/business unit"
              }
            }
          ]
        },
        {
          "name": "Highly Confidential",
          "tooltip": "Highly sensitive data requiring strict access controls and encryption",
          "color": "#D13438",
          "sublabels": [
            {
              "name": "Internal",
              "tooltip": "Encrypted - highly sensitive internal-only content",
              "encryption": true,
              "contentMarking": {
                "headerText": "HIGHLY CONFIDENTIAL - Internal",
                "footerText": "Encrypted - do not share outside the organization"
              }
            },
            {
              "name": "Recipients-Only",
              "tooltip": "Encrypted - accessible only to named recipients",
              "encryption": true,
              "contentMarking": {
                "headerText": "HIGHLY CONFIDENTIAL - Recipients Only",
                "footerText": "Encrypted and restricted to named recipients"
              }
            },
            {
              "name": "Anyone-No-Forwarding",
              "tooltip": "Encrypted - recipients can read but cannot forward, copy, or print",
              "encryption": true,
              "contentMarking": {
                "headerText": "HIGHLY CONFIDENTIAL - Do Not Forward",
                "footerText": "Forwarding, copying, and printing are disabled"
              }
            },
            {
              "name": "Regulated-Data",
              "tooltip": "Encrypted - regulated data (PII, PCI, PHI, financial). Block all external egress.",
              "encryption": true,
              "contentMarking": {
                "headerText": "HIGHLY CONFIDENTIAL - Regulated Data",
                "footerText": "Subject to regulatory protection. External egress blocked by DLP."
              }
            },
            {
              "name": "Vertical-Specific",
              "tooltip": "Encrypted - vertical-specific scoping (e.g., medical, executive, board-only).",
              "encryption": true,
              "contentMarking": {
                "headerText": "HIGHLY CONFIDENTIAL - Vertical-Specific",
                "footerText": "Restricted to authorized vertical/business unit"
              }
            }
          ]
        }
      ],
      "autoLabelPolicies": [
        {
          "name": "Auto-label SSN as Highly Confidential Regulated-Data",
          "labelName": "Highly Confidential\\Regulated-Data",
          "sensitiveInfoTypes": [
            "U.S. Social Security Number (SSN)"
          ],
          "locations": [
            "Exchange",
            "SharePoint",
            "OneDrive"
          ]
        },
        {
          "name": "Auto-label Credit Card as Highly Confidential Regulated-Data",
          "labelName": "Highly Confidential\\Regulated-Data",
          "sensitiveInfoTypes": [
            "Credit Card Number"
          ],
          "locations": [
            "Exchange",
            "SharePoint",
            "OneDrive"
          ]
        },
        {
          "name": "Auto-label Internal-Corp Identifiers as Confidential Internal",
          "labelName": "Confidential\\Internal",
          "sensitiveInfoTypes": [
            "U.S. Employer Identification Number (EIN)",
            "International Banking Account Number (IBAN)",
            "SWIFT Code"
          ],
          "locations": [
            "Exchange",
            "SharePoint",
            "OneDrive"
          ]
        }
      ]
    },
    "retention": {
      "enabled": true,
      "policies": [
        {
          "name": "Financial Records Retention",
          "retentionDays": 2555,
          "retentionAction": "retainAndDelete",
          "locations": [
            "Exchange",
            "SharePoint"
          ]
        },
        {
          "name": "Legal Hold Policy",
          "retentionDays": 365,
          "retentionAction": "retainOnly",
          "locations": [
            "Exchange",
            "OneDrive"
          ]
        }
      ]
    },
    "eDiscovery": {
      "enabled": true,
      "cases": [
        {
          "name": "Data-Breach-Investigation",
          "description": "Investigation into potential data breach involving unauthorized access to confidential financial records and PII",
          "custodians": [
            "mchen@MngEnvMCAP648165.onmicrosoft.com",
            "jblake@MngEnvMCAP648165.onmicrosoft.com",
            "pnair@MngEnvMCAP648165.onmicrosoft.com",
            "msullivan@MngEnvMCAP648165.onmicrosoft.com"
          ],
          "holdQuery": "(subject:\"confidential\" OR subject:\"classified\" OR body:\"breach\" OR body:\"unauthorized\") AND received>=2025-01-01",
          "searchQuery": "breach OR incident",
          "searches": [
            {
              "name": "Financial-Records",
              "contentQuery": "subject:\"financial\" OR body:\"wire transfer\" OR body:\"account number\"",
              "dataSourceScopes": "allCaseCustodians"
            },
            {
              "name": "PII-Exfil",
              "contentQuery": "body:\"social security\" OR body:\"SSN\" OR body:\"credit card\"",
              "dataSourceScopes": "allCaseCustodians"
            },
            {
              "name": "Suspicious-Activity",
              "contentQuery": "subject:\"suspicious\" OR body:\"unauthorized access\" OR body:\"breach\"",
              "dataSourceScopes": "allCaseCustodians"
            }
          ],
          "reviewSets": [
            {
              "name": "Financial-Review",
              "sourceSearch": "Financial-Records"
            },
            {
              "name": "PII-Review",
              "sourceSearch": "PII-Exfil"
            },
            {
              "name": "Incident-Review",
              "sourceSearch": "Suspicious-Activity"
            }
          ]
        },
        {
          "name": "HR-Investigation",
          "description": "HR investigation into workplace conduct allegations including harassment, inappropriate communications, and policy violations.",
          "custodians": [
            "rtorres@MngEnvMCAP648165.onmicrosoft.com",
            "pnair@MngEnvMCAP648165.onmicrosoft.com",
            "nbrooks@MngEnvMCAP648165.onmicrosoft.com",
            "msullivan@MngEnvMCAP648165.onmicrosoft.com"
          ],
          "holdQuery": "(subject:\"complaint\" OR subject:\"investigation\" OR body:\"harassment\" OR body:\"misconduct\" OR body:\"hostile\") AND received>=2025-01-01",
          "searches": [
            {
              "name": "Harassment-Complaints",
              "contentQuery": "body:\"harassment\" OR body:\"hostile\" OR body:\"inappropriate behavior\"",
              "dataSourceScopes": "allCaseCustodians"
            },
            {
              "name": "Termination-Records",
              "contentQuery": "subject:\"termination\" OR body:\"severance\" OR body:\"departure\" OR body:\"resignation\"",
              "dataSourceScopes": "allCaseCustodians"
            },
            {
              "name": "Background-Check-PII",
              "contentQuery": "body:\"social security\" OR body:\"SSN\" OR body:\"date of birth\" OR body:\"background check\"",
              "dataSourceScopes": "allCaseCustodians"
            }
          ],
          "reviewSets": [
            {
              "name": "Conduct-Review",
              "sourceSearch": "Harassment-Complaints"
            },
            {
              "name": "Separation-Review",
              "sourceSearch": "Termination-Records"
            },
            {
              "name": "PII-Review",
              "sourceSearch": "Background-Check-PII"
            }
          ]
        }
      ]
    },
    "communicationCompliance": {
      "enabled": true,
      "policies": [
        {
          "name": "Workplace AI Activity Monitoring",
          "description": "DSPM for AI collection policy - captures AI prompt/response activity for compliance review (Copilot experiences and enterprise AI apps)."
        }
      ]
    },
    "insiderRisk": {
      "enabled": true,
      "policies": [
        {
          "name": "Departing User Data Theft",
          "template": "Data theft by departing users",
          "priorityUserGroups": [
            "PVLab-Executives"
          ],
          "triggeringEvents": [
            "HrEvent",
            "AzureAccountDeleted",
            "UserPerformsExfiltrationActivity"
          ],
          "thresholds": "Default",
          "indicators": [
            "SendingAttachmentsToExternalRecipients",
            "SendingEmailsWithAttachmentsToExternalRecipients",
            "SharePointFileAccessed",
            "SharePointFileDownloaded",
            "SharePointFileDeleted",
            "SharePointFileShared",
            "SharePointDownloadsFromUnallowedDomains",
            "FileCopiedToRemovableMedia",
            "FileCopiedToNetworkShare",
            "FileCopiedToPersonalCloud",
            "FilePrinted",
            "FileRenamedOnDevice",
            "FileArchivedOnDevice",
            "FileDeletedOnDevice",
            "FileCreatedOnDeviceFromCloud",
            "FileDownloadedFromCloudStorage",
            "FileUploadedToCloudStorageViaBrowser",
            "FileUploadedToUnallowedDomainViaBrowser",
            "CumulativeExfiltrationActivity",
            "UnusualVolumeOfFileDeletions",
            "UnusualVolumeOfFileDownloads",
            "UnusualVolumeOfFileUploads",
            "DefenderForEndpointHighSeverityAlert",
            "DefenderForEndpointMediumSeverityAlert",
            "DefenderForEndpointLowSeverityAlert",
            "PhysicalBadgingSignal"
          ]
        },
        {
          "name": "General-Data-Leaks",
          "template": "General data leaks",
          "description": "Detects broad data-leak signals across Exchange, SharePoint, OneDrive, and endpoint. Scoped to all users.",
          "triggeringEvents": [
            "DlpPolicyMatchHighSeverity",
            "UserPerformsExfiltrationActivity"
          ],
          "thresholds": "Default",
          "indicators": [
            "SendingAttachmentsToExternalRecipients",
            "SendingEmailsWithAttachmentsToExternalRecipients",
            "SharePointFileAccessed",
            "SharePointFileDownloaded",
            "SharePointFileDeleted",
            "SharePointFileShared",
            "SharePointDownloadsFromUnallowedDomains",
            "FileCopiedToRemovableMedia",
            "FileCopiedToNetworkShare",
            "FileCopiedToPersonalCloud",
            "FilePrinted",
            "FileRenamedOnDevice",
            "FileArchivedOnDevice",
            "FileDeletedOnDevice",
            "FileCreatedOnDeviceFromCloud",
            "FileDownloadedFromCloudStorage",
            "FileUploadedToCloudStorageViaBrowser",
            "FileUploadedToUnallowedDomainViaBrowser",
            "CumulativeExfiltrationActivity",
            "UnusualVolumeOfFileDeletions",
            "UnusualVolumeOfFileDownloads",
            "UnusualVolumeOfFileUploads",
            "DefenderForEndpointHighSeverityAlert",
            "DefenderForEndpointMediumSeverityAlert",
            "DefenderForEndpointLowSeverityAlert",
            "PhysicalBadgingSignal"
          ]
        },
        {
          "name": "Priority-Executive-Data-Exfil",
          "template": "Data leaks by priority users",
          "description": "Elevated risk scoring for the Executives group. Applies priority indicators.",
          "priorityUserGroups": [
            "PVLab-Executives"
          ],
          "triggeringEvents": [
            "DlpPolicyMatchHighSeverity",
            "UserPerformsExfiltrationActivity"
          ],
          "thresholds": "Default",
          "indicators": [
            "SendingAttachmentsToExternalRecipients",
            "SendingEmailsWithAttachmentsToExternalRecipients",
            "SharePointFileAccessed",
            "SharePointFileDownloaded",
            "SharePointFileDeleted",
            "SharePointFileShared",
            "SharePointDownloadsFromUnallowedDomains",
            "FileCopiedToRemovableMedia",
            "FileCopiedToNetworkShare",
            "FileCopiedToPersonalCloud",
            "FilePrinted",
            "FileRenamedOnDevice",
            "FileArchivedOnDevice",
            "FileDeletedOnDevice",
            "FileCreatedOnDeviceFromCloud",
            "FileDownloadedFromCloudStorage",
            "FileUploadedToCloudStorageViaBrowser",
            "FileUploadedToUnallowedDomainViaBrowser",
            "CumulativeExfiltrationActivity",
            "UnusualVolumeOfFileDeletions",
            "UnusualVolumeOfFileDownloads",
            "UnusualVolumeOfFileUploads",
            "DefenderForEndpointHighSeverityAlert",
            "DefenderForEndpointMediumSeverityAlert",
            "DefenderForEndpointLowSeverityAlert",
            "PhysicalBadgingSignal"
          ]
        },
        {
          "name": "Security-Policy-Violations",
          "template": "Security policy violations",
          "description": "Detects users triggering malware, unusual external logins, or endpoint security violations.",
          "triggeringEvents": [
            "DefenderForEndpointAlert"
          ],
          "thresholds": "Default",
          "indicators": [
            "SendingAttachmentsToExternalRecipients",
            "SendingEmailsWithAttachmentsToExternalRecipients",
            "SharePointFileAccessed",
            "SharePointFileDownloaded",
            "SharePointFileDeleted",
            "SharePointFileShared",
            "SharePointDownloadsFromUnallowedDomains",
            "FileCopiedToRemovableMedia",
            "FileCopiedToNetworkShare",
            "FileCopiedToPersonalCloud",
            "FilePrinted",
            "FileRenamedOnDevice",
            "FileArchivedOnDevice",
            "FileDeletedOnDevice",
            "FileCreatedOnDeviceFromCloud",
            "FileDownloadedFromCloudStorage",
            "FileUploadedToCloudStorageViaBrowser",
            "FileUploadedToUnallowedDomainViaBrowser",
            "CumulativeExfiltrationActivity",
            "UnusualVolumeOfFileDeletions",
            "UnusualVolumeOfFileDownloads",
            "UnusualVolumeOfFileUploads",
            "DefenderForEndpointHighSeverityAlert",
            "DefenderForEndpointMediumSeverityAlert",
            "DefenderForEndpointLowSeverityAlert",
            "PhysicalBadgingSignal"
          ]
        }
      ]
    },
    "testData": {
      "enabled": true,
      "emails": [
        {
          "from": "mchen",
          "to": "jblake",
          "subject": "Q4 Financial Summary - Confidential",
          "body": "Hi Jonathan, attached is the Q4 financial summary. For reference, the wire transfer was initiated from account 0012345678 (routing 021000021). Please review before the board meeting. This information is strictly confidential."
        },
        {
          "from": "sreeves",
          "to": "mchen",
          "subject": "Client Payment Issue",
          "body": "Marcus, the client provided their credit card for the overdue invoice: 4111-1111-1111-1111, exp 12/27. Can you process this through the payment portal? Let me know if you need additional details."
        },
        {
          "from": "rtorres",
          "to": "nbrooks",
          "subject": "Employee Background Check Results",
          "body": "Natalie, here are the background check results for the new hire. SSN on file: 123-45-6789. Everything came back clean. Please file this with the other onboarding documents and mark as confidential."
        },
        {
          "from": "dokafor",
          "to": "jblake",
          "subject": "Suspicious Activity - Insider Trading Concern",
          "body": "Jonathan, I flagged unusual data access patterns from a departing employee. They downloaded several files related to the upcoming merger, including documents marked classified. This could indicate insider trading risk. We should initiate a breach investigation immediately."
        },
        {
          "from": "pnair",
          "to": "rtorres",
          "subject": "Employee Investigation Packet - Confidential",
          "body": "Rachel, legal requested the employee investigation packet for case HR-2026-118. The file includes SSN 512-84-7731, compensation adjustments, and disciplinary notes. Please store this in the restricted HR workspace and share only with Legal."
        },
        {
          "from": "msullivan",
          "to": "pnair",
          "subject": "Workplace Accommodation Documentation",
          "body": "Priya, occupational health completed review for employee accommodation request 24-771. Documentation includes physician statement, treatment plan, and return-to-work restrictions through 05/31. Please retain per HR medical records policy."
        },
        {
          "from": "mchen",
          "to": "rtorres",
          "subject": "Bulk Customer SSN Reconciliation - Q4 Audit",
          "body": "Rachel, attached is the bulk SSN reconciliation pull for the Q4 external audit. Records on file: 123-45-6789, 234-56-7890, 345-67-8901, 456-78-9012, 567-89-0123. Need this reviewed and acknowledged by EOD. The auditors expect formal sign-off before they can finalize the engagement."
        }
      ]
    },
    "auditConfig": {
      "enabled": true,
      "searches": [
        {
          "name": "DLP-Match-Audit",
          "operations": [
            "DlpRuleMatch"
          ]
        },
        {
          "name": "DLP-Override-Audit",
          "operations": [
            "DlpRuleUndo"
          ]
        },
        {
          "name": "File-Access-Audit",
          "operations": [
            "FileAccessed",
            "FileDownloaded",
            "FileModified",
            "FileUploaded"
          ]
        },
        {
          "name": "Sharing-Audit",
          "operations": [
            "SharingInvitationCreated",
            "SharingInvitationAccepted",
            "AnonymousLinkCreated",
            "SecureLinkCreated",
            "SharingSet"
          ]
        },
        {
          "name": "Mailbox-Permission-Audit",
          "operations": [
            "Add-MailboxPermission",
            "Remove-MailboxPermission",
            "New-InboxRule",
            "Set-InboxRule"
          ]
        },
        {
          "name": "Admin-Role-Audit",
          "operations": [
            "Add member to role.",
            "Remove member from role.",
            "Add user.",
            "Delete user."
          ]
        },
        {
          "name": "Sign-In-Failure-Audit",
          "operations": [
            "UserLoginFailed"
          ]
        }
      ]
    },
    "conditionalAccess": {
      "enabled": true,
      "policies": [
        {
          "name": "Require-MFA-AllUsers",
          "description": "Report-only: require MFA for all users across all cloud apps. Evaluates only; does not enforce.",
          "targetAppIds": [
            "All"
          ],
          "action": "mfa",
          "state": "enabledForReportingButNotEnforced"
        },
        {
          "name": "Block-HighRisk-SignIns",
          "description": "Report-only: block sign-ins flagged as high risk by Identity Protection.",
          "targetAppIds": [
            "All"
          ],
          "signInRiskLevels": [
            "high"
          ],
          "action": "block",
          "state": "enabledForReportingButNotEnforced"
        },
        {
          "name": "Require-Compliant-Device",
          "description": "Report-only: require a Intune-compliant or hybrid-joined device for all cloud apps.",
          "targetAppIds": [
            "All"
          ],
          "action": "compliantDevice",
          "state": "enabledForReportingButNotEnforced"
        }
      ]
    }
  },
  "cloud": "commercial"
}
