{
  "labName": "eDiscovery & Retention Demo",
  "prefix": "PVLab",
  "domain": "MngEnvMCAP648165.onmicrosoft.com",
  "workloads": {
    "testUsers": {
      "enabled": true,
      "users": [
        {
          "upn": "nbrooks@MngEnvMCAP648165.onmicrosoft.com"
        },
        {
          "upn": "rtorres@MngEnvMCAP648165.onmicrosoft.com"
        },
        {
          "upn": "mchen@MngEnvMCAP648165.onmicrosoft.com"
        }
      ],
      "groups": [],
      "mode": "existing"
    },
    "dlp": {
      "enabled": false
    },
    "sensitivityLabels": {
      "enabled": false
    },
    "retention": {
      "enabled": true,
      "policies": [
        {
          "name": "Financial Records Retention",
          "retentionDays": 2555,
          "locations": [
            "Exchange",
            "SharePoint"
          ],
          "retentionAction": "retainAndDelete"
        },
        {
          "name": "Legal Hold Policy",
          "retentionDays": 365,
          "locations": [
            "Exchange",
            "OneDrive"
          ],
          "retentionAction": "retainOnly"
        }
      ]
    },
    "eDiscovery": {
      "enabled": true,
      "cases": [
        {
          "name": "Data-Breach-Investigation",
          "description": "Investigation into potential data breach involving financial records",
          "custodians": [
            "rtorres@MngEnvMCAP648165.onmicrosoft.com",
            "mchen@MngEnvMCAP648165.onmicrosoft.com"
          ],
          "holdQuery": "confidential OR classified OR \"data breach\"",
          "searchQuery": "breach OR incident OR unauthorized OR \"data loss\""
        }
      ]
    },
    "communicationCompliance": {
      "enabled": false
    },
    "insiderRisk": {
      "enabled": false
    },
    "testData": {
      "enabled": true,
      "emails": [
        {
          "from": "mchen",
          "to": "rtorres",
          "subject": "Confidential: Security Incident Report",
          "body": "Emily,\n\nWe detected unauthorized access to the financial database. This is classified information - please do not share outside legal.\n\nThe breach occurred on March 10th. We're still assessing the scope of data loss.\n\nRobert"
        },
        {
          "from": "rtorres",
          "to": "nbrooks",
          "subject": "RE: Data Breach - Legal Review Required",
          "body": "James,\n\nPlease review the incident report. We may need to issue breach notifications. This involves confidential customer data.\n\nEmily"
        }
      ]
    }
  },
  "cloud": "commercial"
}
